hstaxe/__init__.py
hstaxe/_version.py
hstaxe/axeException.py
hstaxe/axeerror.py
hstaxe/config.py
hstaxe/utils.py
hstaxe/axesim/WCSdata.py
hstaxe/axesim/__init__.py
hstaxe/axesim/axesim_verify.py
hstaxe/axesim/axesimtasks.py
hstaxe/axesim/imagemaker.py
hstaxe/axesim/interpolator.py
hstaxe/axesim/modspeclist.py
hstaxe/axesim/realworld.py
hstaxe/axesim/templateimages.py
hstaxe/axesim/templatespectra.py
hstaxe/axesrc/__init__.py
hstaxe/axesrc/axecommands.py
hstaxe/axesrc/axeinputs.py
hstaxe/axesrc/axeiol.py
hstaxe/axesrc/axelowlev.py
hstaxe/axesrc/axepreptor.py
hstaxe/axesrc/axesingextr.py
hstaxe/axesrc/axetasks.py
hstaxe/axesrc/configfile.py
hstaxe/axesrc/dither.py
hstaxe/axesrc/dppdumps.py
hstaxe/axesrc/drizzleobjects.py
hstaxe/axesrc/fcubeobjs.py
hstaxe/axesrc/imagemaker.py
hstaxe/axesrc/inputchecks.py
hstaxe/axesrc/iolmaking.py
hstaxe/axesrc/mefobjects.py
hstaxe/axesrc/nlincoeffs.py
hstaxe/axesrc/pysex2gol.py
hstaxe/tests/coveragerc
hstaxe/tests/run_acs_cookbook.py
hstaxe/tests/run_cookbook.py
hstaxe/tests/run_cookbook_part2.py
hstaxe/tests/test_af2pet.py
hstaxe/tests/test_axecore.py
hstaxe/tests/test_axeprep.py
hstaxe/tests/test_be.py
hstaxe/tests/test_gol2af.py
hstaxe/tests/test_iolprep.py
hstaxe/tests/test_pet2spc.py
hstaxe/tests/test_petcont.py
hstaxe/tests/test_petff.py
hstaxe/tests/test_scalebck.py
hstaxe/tests/test_sex2gol.py
hstaxe/tests/test_stamps.py
hstaxe-1.0.5.dist-info/METADATA
hstaxe-1.0.5.dist-info/WHEEL
hstaxe-1.0.5.dist-info/licenses/LICENSE.txt
hstaxe-1.0.5.dist-info/RECORD
