Metadata-Version: 2.1
Name: hstaxe
Version: 1.0.5
Summary: Spectral extraction tools for Hubble Space Telescope Grisms
Project-URL: Homepage, https://github.com/spacetelescope/hstaxe
Author-email: hstaxe and aXe developers <help@stsci.edu>
License-File: LICENSE.txt
Classifier: Development Status :: 5 - Production/Stable
Classifier: Intended Audience :: Science/Research
Classifier: License :: OSI Approved :: GNU General Public License v3 (GPLv3)
Classifier: Programming Language :: C
Classifier: Programming Language :: Python
Classifier: Programming Language :: Python :: 3
Classifier: Programming Language :: Python :: Implementation :: CPython
Classifier: Topic :: Scientific/Engineering :: Astronomy
Classifier: Topic :: Software Development :: Libraries :: Python Modules
Requires-Dist: astropy
Requires-Dist: drizzle
Requires-Dist: drizzlepac
Requires-Dist: numpy<1.24
Requires-Dist: stsci-imagestats
Requires-Dist: stwcs
Provides-Extra: docs
Requires-Dist: sphinx; extra == 'docs'
Requires-Dist: sphinx-automodapi; extra == 'docs'
Requires-Dist: sphinx-rtd-theme; extra == 'docs'
Requires-Dist: stsci-rtd-theme; extra == 'docs'
Provides-Extra: test
Requires-Dist: backports-tempfile; extra == 'test'
Requires-Dist: pytest; extra == 'test'
Requires-Dist: pytest-catchlog; extra == 'test'
Requires-Dist: requests-mock; extra == 'test'
